deepsig/__init__.py
deepsig/aso.py
deepsig/bootstrap.py
deepsig/conversion.py
deepsig/correction.py
deepsig/permutation.py
deepsig/sample_size.py
deepsig/utils.py
deepsig/tests/__init__.py
deepsig/tests/test_aso.py
deepsig/tests/test_bootstrap_permutation.py
deepsig/tests/test_conversion.py
deepsig/tests/test_correction.py
deepsig/tests/test_sample_size.py
deepsig-1.2.8.dist-info/LICENSE
deepsig-1.2.8.dist-info/METADATA
deepsig-1.2.8.dist-info/WHEEL
deepsig-1.2.8.dist-info/top_level.txt
deepsig-1.2.8.dist-info/RECORD
