Metadata-Version: 2.1
Name: deepsig
Version: 1.2.8
Summary: Easy Significance Testing for Deep Neural Networks.
Home-page: https://github.com/Kaleidophon/deep-significance
Author: Dennis Ulmer
License: GPL
Keywords: machine learning,deep learning,reinforcement learning,computer vision,natural language processing,nlp,rl,cv,statistical significance testing,statistical hypothesis testing,significance test,statistical significance,pytorch,tensorflow,numpy,jax
Classifier: Intended Audience :: Science/Research
Classifier: Topic :: Scientific/Engineering :: Artificial Intelligence
Classifier: Programming Language :: Python :: 3
Classifier: Operating System :: OS Independent
Requires-Python: >=3.7.0
License-File: LICENSE
Requires-Dist: numpy >=1.19.5
Requires-Dist: scipy >=1.6.0
Requires-Dist: tqdm >=4.59.0
Requires-Dist: joblib >=1.0.1
Requires-Dist: pandas >=1.3.3
Requires-Dist: dill >=0.3.4
Requires-Dist: psutil >=5.9.0
